{
  "sources": [
    {
      "scheme_id": "hdfc-mid-cap",
      "url": "https://groww.in/mutual-funds/hdfc-mid-cap-fund-direct-growth",
      "status": "ok",
      "last_fetched": "2026-07-05T06:57:01.584634+00:00",
      "content_hash": "sha256:09f8e64ed1ff8aab70b29e1c70ece2dca7078f6f41042d7c0237d54884f5c83f",
      "http_status": 200,
      "error": null,
      "raw_snapshot": "hdfc-mid-cap.html"
    },
    {
      "scheme_id": "hdfc-equity",
      "url": "https://groww.in/mutual-funds/hdfc-equity-fund-direct-growth",
      "status": "ok",
      "last_fetched": "2026-07-05T06:57:01.924062+00:00",
      "content_hash": "sha256:8793baa3dfc849abf4f37f810294252d7c23c46e37cb66db307027526f8eae0b",
      "http_status": 200,
      "error": null,
      "raw_snapshot": "hdfc-equity.html"
    },
    {
      "scheme_id": "hdfc-focused",
      "url": "https://groww.in/mutual-funds/hdfc-focused-fund-direct-growth",
      "status": "ok",
      "last_fetched": "2026-07-05T06:57:02.187218+00:00",
      "content_hash": "sha256:91926c7de9f4a52546ffddbd83bb9ded9628ad47f268dbbf232f4526195fe7e7",
      "http_status": 200,
      "error": null,
      "raw_snapshot": "hdfc-focused.html"
    },
    {
      "scheme_id": "hdfc-elss",
      "url": "https://groww.in/mutual-funds/hdfc-elss-tax-saver-fund-direct-plan-growth",
      "status": "ok",
      "last_fetched": "2026-07-05T06:57:02.572104+00:00",
      "content_hash": "sha256:40abd08a4eeedb871a01262774dd03aa57417649da121f3def134a708bec3876",
      "http_status": 200,
      "error": null,
      "raw_snapshot": "hdfc-elss.html"
    },
    {
      "scheme_id": "hdfc-large-cap",
      "url": "https://groww.in/mutual-funds/hdfc-large-cap-fund-direct-growth",
      "status": "ok",
      "last_fetched": "2026-07-05T06:57:02.847018+00:00",
      "content_hash": "sha256:b0a227965098c59c4668813047227858823373dee4b92b6bb421b25373da9485",
      "http_status": 200,
      "error": null,
      "raw_snapshot": "hdfc-large-cap.html"
    }
  ]
}
